{
  "title": "The Lord Is My Shepherd (Chant)",
  "slug": "the-lord-is-my-shepherd-chant",
  "subtitle": "A simple chant on Psalm 23",
  "lyrics": "[Verse 1]\nThe Lord is my shepherd, I shall not want.\nHe makes me lie down in green pastures.\nHe leads me beside still waters,\nHe restores my soul.\n\n[Chorus]\nMy shepherd, my shepherd,\nYou are enough for me.\nMy shepherd, my shepherd,\nYou are enough for me.\n\n[Verse 2]\nYea, though I walk through the valley\nOf the shadow of death,\nI will fear no evil,\nFor You are with me.\n\n[Chorus]\n\n[Verse 3]\nYou prepare a table before me\nIn the presence of my enemies.\nYou anoint my head with oil,\nMy cup overflows.\n\n[Chorus]\n\n[Bridge]\nSurely goodness and mercy\nShall follow me all the days of my life,\nAnd I will dwell in the house of the Lord\nForever.",
  "chords": "D                A             Bm\nThe Lord is my shepherd, I shall not want\nG                D              A\nHe makes me lie down in green pastures\nD                A             Bm\nHe leads me beside still waters\nG              D       A       D\nHe restores my soul, restores my soul",
  "scripture_refs": [
    "Psalm 23"
  ],
  "reflection": "Sometimes a song is the only prayer we can pray. Sing it slowly. Let the words do what words do.",
  "category": "comfort",
  "key_signature": "D",
  "tempo_bpm": 72,
  "meter": "4/4",
  "day_of_year": 1,
  "sort_order": 1,
  "is_published": true
}
